llm_json_repair/__init__.py
llm_json_repair/extractors.py
llm_json_repair/parser.py
llm_json_repair-1.0.0.dist-info/METADATA
llm_json_repair-1.0.0.dist-info/WHEEL
llm_json_repair-1.0.0.dist-info/licenses/LICENSE
llm_json_repair-1.0.0.dist-info/RECORD
