Metadata-Version: 2.4
Name: llm-json-repair
Version: 1.0.0
Summary: Robust JSON parsing for LLM outputs with automatic repair and field extraction
Project-URL: Homepage, https://github.com/gcrabtree/llm-json-repair
Project-URL: Repository, https://github.com/gcrabtree/llm-json-repair
Project-URL: Issues, https://github.com/gcrabtree/llm-json-repair/issues
Author: Greg Crabtree
License: MIT
License-File: LICENSE
Keywords: ai,claude,gpt,json,llm,parser,repair
Classifier: Development Status :: 5 - Production/Stable
Classifier: Intended Audience :: Developers
Classifier: License :: OSI Approved :: MIT License
Classifier: Operating System :: OS Independent
Classifier: Programming Language :: Python :: 3
Classifier: Programming Language :: Python :: 3.9
Classifier: Programming Language :: Python :: 3.10
Classifier: Programming Language :: Python :: 3.11
Classifier: Programming Language :: Python :: 3.12
Classifier: Topic :: Software Development :: Libraries :: Python Modules
Classifier: Topic :: Text Processing :: General
Requires-Python: >=3.9
Provides-Extra: dev
Requires-Dist: black>=23.0; extra == 'dev'
Requires-Dist: mypy>=1.0; extra == 'dev'
Requires-Dist: pytest-cov>=4.0; extra == 'dev'
Requires-Dist: pytest>=7.0; extra == 'dev'
Requires-Dist: ruff>=0.1; extra == 'dev'
